{
    "metadata": {},
    "content": "{\n    \"source_filename\": \"ClusterPacketCache.yaml\",\n    \"metadata\": {},\n    \"content\": \"# This file is automatically generated. Please don't edit it manually.\\n# To submit a bug report on the content, see\\n# https://devforum.roblox.com/c/bug-reports/documentation-issues/72\\n\\nname: ClusterPacketCache\\ntype: class\\nmemory_category: Instances\\nsummary: |\\n  An internal service meant to cache cluster packets.\\ndescription: |\\n  An internal service meant to cache cluster packets. This service will only be\\n  present if a `Class.NetworkServer` is present.\\ncode_samples: []\\ninherits:\\n  - Instance\\ndescendants: []\\ntags:\\n  - NotCreatable\\n  - Service\\n  - NotReplicated\\ndeprecation_message: ''\\nproperties: []\\nmethods: []\\nevents: []\\ncallbacks: []\"\n}"
}